pymagsac/pymagsac.cp312-win_amd64.pyd
pymagsac/__init__.py
pymagsac-0.2.2.dist-info/DELVEWHEEL
pymagsac-0.2.2.dist-info/LICENSE
pymagsac-0.2.2.dist-info/METADATA
pymagsac-0.2.2.dist-info/RECORD
pymagsac-0.2.2.dist-info/top_level.txt
pymagsac-0.2.2.dist-info/WHEEL
pymagsac.libs/concrt140-d031d818a48157c7cf7ebc34cb905832.dll
pymagsac.libs/msvcp140-11617ccbb317012404ccbd4eacd4c75b.dll
pymagsac.libs/opencv_core345-a3286c462c08c43f2c4bac35236386a9.dll
