Metadata-Version: 2.1
Name: pymagsac
Version: 0.2.2
Summary: MAGSAC and MAGSAC++
Author: Daniel Barath, Dmytro Mishkin
Author-email: barath.daniel@sztaki.hu
License-File: LICENSE
Requires-Dist: numpy
